cosmo_wallet_friends/__init__.py
cosmo_wallet_friends/bot/teste_bot.py
cosmo_wallet_friends/controller.py
cosmo_wallet_friends/main.py
cosmo_wallet_friends/models.py
cosmo_wallet_friends/wallets.py
cosmo_wallet_friends-0.1.2.dist-info/METADATA
cosmo_wallet_friends-0.1.2.dist-info/WHEEL
cosmo_wallet_friends-0.1.2.dist-info/RECORD
