Metadata-Version: 2.1
Name: cosmo-wallet-friends
Version: 0.1.2
Summary: 
Author: Bruno-Felix
Author-email: balvesfelix@gmail.com
Requires-Python: >=3.10,<4.0
Classifier: Programming Language :: Python :: 3
Classifier: Programming Language :: Python :: 3.10
Classifier: Programming Language :: Python :: 3.11
Requires-Dist: requests (>=2.31.0,<3.0.0)
